torchtools
